[{"Country Name": "Afghanistan", "Country Code": "AFG", "years": [{"2010": 48.28708366}]}, {"Country Name": "Africa Eastern and Southern", "Country Code": "AFE", "years": [{"2010": 50.0414306397136}]}, {"Country Name": "Africa Western and Central", "Country Code": "AFW", "years": [{"2010": 61.0914873787084}]}, {"Country Name": "Albania", "Country Code": "ALB", "years": [{"2010": 91.37947821}]}, {"Country Name": "Algeria", "Country Code": "DZA", "years": [{"2010": 92.29597417}]}, {"Country Name": "American Samoa", "Country Code": "ASM", "years": [{"2010": 99.23243189}]}, {"Country Name": "Andorra", "Country Code": "AND", "years": [{"2010": 100.0000023}]}, {"Country Name": "Angola", "Country Code": "AGO", "years": [{"2010": 50.37684093}]}, {"Country Name": "Antigua and Barbuda", "Country Code": "ATG", "years": [{"2010": 97.08870448}]}, {"Country Name": "Arab World", "Country Code": "ARB", "years": [{"2010": 84.5015858721624}]}, {"Country Name": "Argentina", "Country Code": "ARG", "years": [{"2010": 98.42725533}]}, {"Country Name": "Armenia", "Country Code": "ARM", "years": [{"2010": 98.2004766}]}, {"Country Name": "Aruba", "Country Code": "ABW", "years": [{"2010": 97.30565388}]}, {"Country Name": "Australia", "Country Code": "AUS", "years": [{"2010": 99.88315015}]}, {"Country Name": "Austria", "Country Code": "AUT", "years": [{"2010": 100.0000029}]}, {"Country Name": "Azerbaijan", "Country Code": "AZE", "years": [{"2010": 85.97105431}]}, {"Country Name": "Bahamas, The", "Country Code": "BHS", "years": [{"2010": 98.67313887}]}, {"Country Name": "Bahrain", "Country Code": "BHR", "years": [{"2010": 99.98446244}]}, {"Country Name": "Bangladesh", "Country Code": "BGD", "years": [{"2010": 96.39688709}]}, {"Country Name": "Barbados", "Country Code": "BRB", "years": [{"2010": 98.42443765}]}, {"Country Name": "Belarus", "Country Code": "BLR", "years": [{"2010": 97.53976199}]}, {"Country Name": "Belgium", "Country Code": "BEL", "years": [{"2010": 99.99999861}]}, {"Country Name": "Belize", "Country Code": "BLZ", "years": [{"2010": 93.93747934}]}, {"Country Name": "Benin", "Country Code": "BEN", "years": [{"2010": 64.03810265}]}, {"Country Name": "Bermuda", "Country Code": "BMU", "years": [{"2010": 99.91830717}]}, {"Country Name": "Bhutan", "Country Code": "BTN", "years": [{"2010": 92.41428403}]}, {"Country Name": "Bolivia", "Country Code": "BOL", "years": [{"2010": 87.26318343}]}, {"Country Name": "Bosnia and Herzegovina", "Country Code": "BIH", "years": [{"2010": 96.66949483}]}, {"Country Name": "Botswana", "Country Code": "BWA", "years": [{"2010": 83.04816923}]}, {"Country Name": "Brazil", "Country Code": "BRA", "years": [{"2010": 96.51879691}]}, {"Country Name": "British Virgin Islands", "Country Code": "VGB", "years": [{"2010": 99.10410959}]}, {"Country Name": "Brunei Darussalam", "Country Code": "BRN", "years": [{"2010": 99.49976796}]}, {"Country Name": "Bulgaria", "Country Code": "BGR", "years": [{"2010": 99.39938391}]}, {"Country Name": "Burkina Faso", "Country Code": "BFA", "years": [{"2010": 53.15173453}]}, {"Country Name": "Burundi", "Country Code": "BDI", "years": [{"2010": 56.52311691}]}, {"Country Name": "Cabo Verde", "Country Code": "CPV", "years": [{"2010": 82.99094948}]}, {"Country Name": "Cambodia", "Country Code": "KHM", "years": [{"2010": 64.73036087}]}, {"Country Name": "Cameroon", "Country Code": "CMR", "years": [{"2010": 62.03643519}]}, {"Country Name": "Canada", "Country Code": "CAN", "years": [{"2010": 99.23634886}]}, {"Country Name": "Caribbean small states", "Country Code": "CSS", "years": [{"2010": 93.6177511296645}]}, {"Country Name": "Cayman Islands", "Country Code": "CYM", "years": [{"2010": 96.125}]}, {"Country Name": "Central African Republic", "Country Code": "CAF", "years": [{"2010": 47.61218174}]}, {"Country Name": "Central Europe and the Baltics", "Country Code": "CEB", "years": [{"2010": 98.980978669987}]}, {"Country Name": "Chad", "Country Code": "TCD", "years": [{"2010": 42.72317538}]}, {"Country Name": "Channel Islands", "Country Code": "CHI", "years": [{"2010": 94.15}]}, {"Country Name": "Chile", "Country Code": "CHL", "years": [{"2010": 98.32901085}]}, {"Country Name": "China", "Country Code": "CHN", "years": [{"2010": 88.56889093}]}, {"Country Name": "Colombia", "Country Code": "COL", "years": [{"2010": 94.85395872}]}, {"Country Name": "Comoros", "Country Code": "COM", "years": [{"2010": 83.40597974}]}, {"Country Name": "Congo, Dem. Rep.", "Country Code": "COD", "years": [{"2010": 39.60194826}]}, {"Country Name": "Congo, Rep.", "Country Code": "COG", "years": [{"2010": 65.89391032}]}, {"Country Name": "Costa Rica", "Country Code": "CRI", "years": [{"2010": 98.11229116}]}, {"Country Name": "Cote d'Ivoire", "Country Code": "CIV", "years": [{"2010": 71.23152598}]}, {"Country Name": "Croatia", "Country Code": "HRV", "years": [{"2010": null}]}, {"Country Name": "Cuba", "Country Code": "CUB", "years": [{"2010": 94.73274925}]}, {"Country Name": "Curacao", "Country Code": "CUW", "years": [{"2010": 99.3102419}]}, {"Country Name": "Cyprus", "Country Code": "CYP", "years": [{"2010": 99.82714804}]}, {"Country Name": "Czechia", "Country Code": "CZE", "years": [{"2010": 99.85659774}]}, {"Country Name": "Denmark", "Country Code": "DNK", "years": [{"2010": 100.0000022}]}, {"Country Name": "Djibouti", "Country Code": "DJI", "years": [{"2010": 75.61980786}]}, {"Country Name": "Dominica", "Country Code": "DMA", "years": [{"2010": 95.05390905}]}, {"Country Name": "Dominican Republic", "Country Code": "DOM", "years": [{"2010": 94.54420957}]}, {"Country Name": "Early-demographic dividend", "Country Code": "EAR", "years": [{"2010": 85.7635388463475}]}, {"Country Name": "East Asia & Pacific", "Country Code": "EAS", "years": [{"2010": 88.7331198204404}]}, {"Country Name": "East Asia & Pacific (IDA & IBRD countries)", "Country Code": "TEA", "years": [{"2010": 87.4779459460654}]}, {"Country Name": "East Asia & Pacific (excluding high income)", "Country Code": "EAP", "years": [{"2010": 87.5977613602659}]}, {"Country Name": "Ecuador", "Country Code": "ECU", "years": [{"2010": 89.53052651}]}, {"Country Name": "Egypt, Arab Rep.", "Country Code": "EGY", "years": [{"2010": 98.70241581}]}, {"Country Name": "El Salvador", "Country Code": "SLV", "years": [{"2010": 89.66189951}]}, {"Country Name": "Equatorial Guinea", "Country Code": "GNQ", "years": [{"2010": 60.44136312}]}, {"Country Name": "Eritrea", "Country Code": "ERI", "years": [{"2010": 49.97738165}]}, {"Country Name": "Estonia", "Country Code": "EST", "years": [{"2010": 99.74892504}]}, {"Country Name": "Eswatini", "Country Code": "SWZ", "years": [{"2010": 62.15507375}]}, {"Country Name": "Ethiopia", "Country Code": "ETH", "years": [{"2010": 34.16251912}]}, {"Country Name": "Euro area", "Country Code": "EMU", "years": [{"2010": 99.8195838651354}]}, {"Country Name": "Europe & Central Asia", "Country Code": "ECS", "years": [{"2010": 97.5809398536744}]}, {"Country Name": "Europe & Central Asia (IDA & IBRD countries)", "Country Code": "TEC", "years": [{"2010": 95.2489689233515}]}, {"Country Name": "Europe & Central Asia (excluding high income)", "Country Code": "ECA", "years": [{"2010": 94.6887664410584}]}, {"Country Name": "European Union", "Country Code": "EUU", "years": [{"2010": 99.6898517662643}]}, {"Country Name": "Faroe Islands", "Country Code": "FRO", "years": [{"2010": 100.0}]}, {"Country Name": "Fiji", "Country Code": "FJI", "years": [{"2010": 94.27917122}]}, {"Country Name": "Finland", "Country Code": "FIN", "years": [{"2010": 100.0}]}, {"Country Name": "Fragile and conflict affected situations", "Country Code": "FCS", "years": [{"2010": 58.9750034420621}]}, {"Country Name": "France", "Country Code": "FRA", "years": [{"2010": 99.97524196}]}, {"Country Name": "French Polynesia", "Country Code": "PYF", "years": [{"2010": 100.0}]}, {"Country Name": "Gabon", "Country Code": "GAB", "years": [{"2010": 82.99105522}]}, {"Country Name": "Gambia, The", "Country Code": "GMB", "years": [{"2010": 77.44704825}]}, {"Country Name": "Georgia", "Country Code": "GEO", "years": [{"2010": 95.10987098}]}, {"Country Name": "Germany", "Country Code": "DEU", "years": [{"2010": 100.0}]}, {"Country Name": "Ghana", "Country Code": "GHA", "years": [{"2010": 74.584619}]}, {"Country Name": "Gibraltar", "Country Code": "GIB", "years": [{"2010": 100.0}]}, {"Country Name": "Greece", "Country Code": "GRC", "years": [{"2010": 99.92007062}]}, {"Country Name": "Greenland", "Country Code": "GRL", "years": [{"2010": 99.99999832}]}, {"Country Name": "Grenada", "Country Code": "GRD", "years": [{"2010": 95.63078751}]}, {"Country Name": "Guam", "Country Code": "GUM", "years": [{"2010": 99.646}]}, {"Country Name": "Guatemala", "Country Code": "GTM", "years": [{"2010": 90.30204843}]}, {"Country Name": "Guinea", "Country Code": "GIN", "years": [{"2010": 62.7995854}]}, {"Country Name": "Guinea-Bissau", "Country Code": "GNB", "years": [{"2010": 58.16667149}]}, {"Country Name": "Guyana", "Country Code": "GUY", "years": [{"2010": 92.6391237}]}, {"Country Name": "Haiti", "Country Code": "HTI", "years": [{"2010": 62.20079017}]}, {"Country Name": "Heavily indebted poor countries (HIPC)", "Country Code": "HPC", "years": [{"2010": 50.8812624110921}]}, {"Country Name": "High income", "Country Code": "HIC", "years": [{"2010": 99.2697763599966}]}, {"Country Name": "Honduras", "Country Code": "HND", "years": [{"2010": 90.70079936}]}, {"Country Name": "Hong Kong SAR, China", "Country Code": "HKG", "years": [{"2010": 99.5819416}]}, {"Country Name": "Hungary", "Country Code": "HUN", "years": [{"2010": 99.96892877}]}, {"Country Name": "IBRD only", "Country Code": "IBD", "years": [{"2010": null}]}, {"Country Name": "IDA & IBRD total", "Country Code": "IBT", "years": [{"2010": 83.6582737841067}]}, {"Country Name": "IDA blend", "Country Code": "IDB", "years": [{"2010": null}]}, {"Country Name": "IDA only", "Country Code": "IDX", "years": [{"2010": null}]}, {"Country Name": "IDA total", "Country Code": "IDA", "years": [{"2010": null}]}, {"Country Name": "Iceland", "Country Code": "ISL", "years": [{"2010": 100.0000018}]}, {"Country Name": "India", "Country Code": "IND", "years": [{"2010": 85.68425222}]}, {"Country Name": "Indonesia", "Country Code": "IDN", "years": [{"2010": 84.43671954}]}, {"Country Name": "Iran, Islamic Rep.", "Country Code": "IRN", "years": [{"2010": 96.03812638}]}, {"Country Name": "Iraq", "Country Code": "IRQ", "years": [{"2010": 89.74768575}]}, {"Country Name": "Ireland", "Country Code": "IRL", "years": [{"2010": 97.31290582}]}, {"Country Name": "Isle of Man", "Country Code": "IMN", "years": [{"2010": 99.075}]}, {"Country Name": "Israel", "Country Code": "ISR", "years": [{"2010": 100.0000017}]}, {"Country Name": "Italy", "Country Code": "ITA", "years": [{"2010": 99.81418421}]}, {"Country Name": "Jamaica", "Country Code": "JAM", "years": [{"2010": 91.23834343}]}, {"Country Name": "Japan", "Country Code": "JPN", "years": [{"2010": 98.72767177}]}, {"Country Name": "Jordan", "Country Code": "JOR", "years": [{"2010": 99.01634056}]}, {"Country Name": "Kazakhstan", "Country Code": "KAZ", "years": [{"2010": 93.65814893}]}, {"Country Name": "Kenya", "Country Code": "KEN", "years": [{"2010": 54.66210303}]}, {"Country Name": "Kiribati", "Country Code": "KIR", "years": [{"2010": 69.46864124}]}, {"Country Name": "Korea, Dem. People's Rep.", "Country Code": "PRK", "years": [{"2010": 97.0141858}]}, {"Country Name": "Korea, Rep.", "Country Code": "KOR", "years": [{"2010": 99.01409617}]}, {"Country Name": "Kosovo", "Country Code": "XKX", "years": [{"2010": null}]}, {"Country Name": "Kuwait", "Country Code": "KWT", "years": [{"2010": 100.0}]}, {"Country Name": "Kyrgyz Republic", "Country Code": "KGZ", "years": [{"2010": 85.39985284}]}, {"Country Name": "Lao PDR", "Country Code": "LAO", "years": [{"2010": 67.86004979}]}, {"Country Name": "Late-demographic dividend", "Country Code": "LTE", "years": [{"2010": 90.8508078962675}]}, {"Country Name": "Latin America & Caribbean", "Country Code": "LCN", "years": [{"2010": 94.4103773064188}]}, {"Country Name": "Latin America & Caribbean (excluding high income)", "Country Code": "LAC", "years": [{"2010": 94.1769009351368}]}, {"Country Name": "Latin America & the Caribbean (IDA & IBRD countries)", "Country Code": "TLA", "years": [{"2010": 94.3682313337712}]}, {"Country Name": "Latvia", "Country Code": "LVA", "years": [{"2010": 98.26631221}]}, {"Country Name": "Least developed countries: UN classification", "Country Code": "LDC", "years": [{"2010": 58.6839081314326}]}, {"Country Name": "Lebanon", "Country Code": "LBN", "years": [{"2010": 89.4421822}]}, {"Country Name": "Lesotho", "Country Code": "LSO", "years": [{"2010": 69.04535237}]}, {"Country Name": "Liberia", "Country Code": "LBR", "years": [{"2010": 69.55329165}]}, {"Country Name": "Libya", "Country Code": "LBY", "years": [{"2010": 92.93176743}]}, {"Country Name": "Liechtenstein", "Country Code": "LIE", "years": [{"2010": 100.0}]}, {"Country Name": "Lithuania", "Country Code": "LTU", "years": [{"2010": 94.24874381}]}, {"Country Name": "Low & middle income", "Country Code": "LMY", "years": [{"2010": 83.4708925572022}]}, {"Country Name": "Low income", "Country Code": "LIC", "years": [{"2010": 50.1046866237495}]}, {"Country Name": "Lower middle income", "Country Code": "LMC", "years": [{"2010": 83.2855902002226}]}, {"Country Name": "Luxembourg", "Country Code": "LUX", "years": [{"2010": 99.999997}]}, {"Country Name": "Macao SAR, China", "Country Code": "MAC", "years": [{"2010": 100.0}]}, {"Country Name": "Madagascar", "Country Code": "MDG", "years": [{"2010": 44.42527631}]}, {"Country Name": "Malawi", "Country Code": "MWI", "years": [{"2010": 62.1485803}]}, {"Country Name": "Malaysia", "Country Code": "MYS", "years": [{"2010": 97.01774688}]}, {"Country Name": "Maldives", "Country Code": "MDV", "years": [{"2010": 97.26818052}]}, {"Country Name": "Mali", "Country Code": "MLI", "years": [{"2010": 66.10227438}]}, {"Country Name": "Malta", "Country Code": "MLT", "years": [{"2010": 99.99999678}]}, {"Country Name": "Marshall Islands", "Country Code": "MHL", "years": [{"2010": 88.01053081}]}, {"Country Name": "Mauritania", "Country Code": "MRT", "years": [{"2010": 57.7803936}]}, {"Country Name": "Mauritius", "Country Code": "MUS", "years": [{"2010": 99.72937337}]}, {"Country Name": "Mexico", "Country Code": "MEX", "years": [{"2010": 95.82133427}]}, {"Country Name": "Micronesia, Fed. Sts.", "Country Code": "FSM", "years": [{"2010": 87.31121061}]}, {"Country Name": "Middle East & North Africa", "Country Code": "MEA", "years": [{"2010": 91.3337145951764}]}, {"Country Name": "Middle East & North Africa (IDA & IBRD countries)", "Country Code": "TMN", "years": [{"2010": 90.1134284498992}]}, {"Country Name": "Middle East & North Africa (excluding high income)", "Country Code": "MNA", "years": [{"2010": 90.1634415156459}]}, {"Country Name": "Middle income", "Country Code": "MIC", "years": [{"2010": 86.8253520793173}]}, {"Country Name": "Moldova", "Country Code": "MDA", "years": [{"2010": 86.62746665}]}, {"Country Name": "Monaco", "Country Code": "MCO", "years": [{"2010": 100.0}]}, {"Country Name": "Mongolia", "Country Code": "MNG", "years": [{"2010": 76.17556961}]}, {"Country Name": "Montenegro", "Country Code": "MNE", "years": [{"2010": 96.164094}]}, {"Country Name": "Morocco", "Country Code": "MAR", "years": [{"2010": 76.72145338}]}, {"Country Name": "Mozambique", "Country Code": "MOZ", "years": [{"2010": 39.73997963}]}, {"Country Name": "Myanmar", "Country Code": "MMR", "years": [{"2010": 64.08560886}]}, {"Country Name": "Namibia", "Country Code": "NAM", "years": [{"2010": 80.52969316}]}, {"Country Name": "Nauru", "Country Code": "NRU", "years": [{"2010": 98.70436165}]}, {"Country Name": "Nepal", "Country Code": "NPL", "years": [{"2010": 85.35823515}]}, {"Country Name": "Netherlands", "Country Code": "NLD", "years": [{"2010": 100.0}]}, {"Country Name": "New Caledonia", "Country Code": "NCL", "years": [{"2010": 96.97179641}]}, {"Country Name": "New Zealand", "Country Code": "NZL", "years": [{"2010": 100.0}]}, {"Country Name": "Nicaragua", "Country Code": "NIC", "years": [{"2010": 81.04894858}]}, {"Country Name": "Niger", "Country Code": "NER", "years": [{"2010": 43.40945251}]}, {"Country Name": "Nigeria", "Country Code": "NGA", "years": [{"2010": 60.0107879}]}, {"Country Name": "North America", "Country Code": "NAC", "years": [{"2010": 99.0046189305832}]}, {"Country Name": "North Macedonia", "Country Code": "MKD", "years": [{"2010": 97.20938509}]}, {"Country Name": "Northern Mariana Islands", "Country Code": "MNP", "years": [{"2010": 98.93466279}]}, {"Country Name": "Norway", "Country Code": "NOR", "years": [{"2010": 100.0000025}]}, {"Country Name": "Not classified", "Country Code": "INX", "years": [{"2010": null}]}, {"Country Name": "OECD members", "Country Code": "OED", "years": [{"2010": 98.6359194145293}]}, {"Country Name": "Oman", "Country Code": "OMN", "years": [{"2010": 87.84044199}]}, {"Country Name": "Other small states", "Country Code": "OSS", "years": [{"2010": 82.7532439307647}]}, {"Country Name": "Pacific island small states", "Country Code": "PSS", "years": [{"2010": 86.8641048542088}]}, {"Country Name": "Pakistan", "Country Code": "PAK", "years": [{"2010": 88.7234313}]}, {"Country Name": "Palau", "Country Code": "PLW", "years": [{"2010": 99.54029006}]}, {"Country Name": "Panama", "Country Code": "PAN", "years": [{"2010": 91.86961969}]}, {"Country Name": "Papua New Guinea", "Country Code": "PNG", "years": [{"2010": 37.70691852}]}, {"Country Name": "Paraguay", "Country Code": "PRY", "years": [{"2010": 90.27575476}]}, {"Country Name": "Peru", "Country Code": "PER", "years": [{"2010": 87.31744155}]}, {"Country Name": "Philippines", "Country Code": "PHL", "years": [{"2010": 89.90463834}]}, {"Country Name": "Poland", "Country Code": "POL", "years": [{"2010": 98.2772052}]}, {"Country Name": "Portugal", "Country Code": "PRT", "years": [{"2010": 99.578895}]}, {"Country Name": "Post-demographic dividend", "Country Code": "PST", "years": [{"2010": 99.1338183092866}]}, {"Country Name": "Pre-demographic dividend", "Country Code": "PRE", "years": [{"2010": 54.5593513479453}]}, {"Country Name": "Puerto Rico", "Country Code": "PRI", "years": [{"2010": 98.68804838}]}, {"Country Name": "Qatar", "Country Code": "QAT", "years": [{"2010": 100.0}]}, {"Country Name": "Romania", "Country Code": "ROU", "years": [{"2010": 100.0}]}, {"Country Name": "Russian Federation", "Country Code": "RUS", "years": [{"2010": 96.07661235}]}, {"Country Name": "Rwanda", "Country Code": "RWA", "years": [{"2010": 53.22144838}]}, {"Country Name": "Samoa", "Country Code": "WSM", "years": [{"2010": 90.19492888}]}, {"Country Name": "San Marino", "Country Code": "SMR", "years": [{"2010": 100.0}]}, {"Country Name": "Sao Tome and Principe", "Country Code": "STP", "years": [{"2010": 74.44411367}]}, {"Country Name": "Saudi Arabia", "Country Code": "SAU", "years": [{"2010": 98.74765073}]}, {"Country Name": "Senegal", "Country Code": "SEN", "years": [{"2010": 72.23202583}]}, {"Country Name": "Serbia", "Country Code": "SRB", "years": [{"2010": 91.49811595}]}, {"Country Name": "Seychelles", "Country Code": "SYC", "years": [{"2010": 95.65603226}]}, {"Country Name": "Sierra Leone", "Country Code": "SLE", "years": [{"2010": 51.82316162}]}, {"Country Name": "Singapore", "Country Code": "SGP", "years": [{"2010": 100.0}]}, {"Country Name": "Sint Maarten (Dutch part)", "Country Code": "SXM", "years": [{"2010": 95.59441034}]}, {"Country Name": "Slovak Republic", "Country Code": "SVK", "years": [{"2010": 98.62233526}]}, {"Country Name": "Slovenia", "Country Code": "SVN", "years": [{"2010": 99.5}]}, {"Country Name": "Small states", "Country Code": "SST", "years": [{"2010": 85.1384139810922}]}, {"Country Name": "Solomon Islands", "Country Code": "SLB", "years": [{"2010": 73.50321438}]}, {"Country Name": "Somalia", "Country Code": "SOM", "years": [{"2010": 40.27195943}]}, {"Country Name": "South Africa", "Country Code": "ZAF", "years": [{"2010": 89.63843841}]}, {"Country Name": "South Asia", "Country Code": "SAS", "years": [{"2010": 86.3749333857768}]}, {"Country Name": "South Asia (IDA & IBRD)", "Country Code": "TSA", "years": [{"2010": 86.3749333857769}]}, {"Country Name": "South Sudan", "Country Code": "SSD", "years": [{"2010": null}]}, {"Country Name": "Spain", "Country Code": "ESP", "years": [{"2010": 100.0}]}, {"Country Name": "Sri Lanka", "Country Code": "LKA", "years": [{"2010": 86.67712252}]}, {"Country Name": "St. Kitts and Nevis", "Country Code": "KNA", "years": [{"2010": 98.57447873}]}, {"Country Name": "St. Lucia", "Country Code": "LCA", "years": [{"2010": 93.36868145}]}, {"Country Name": "St. Martin (French part)", "Country Code": "MAF", "years": [{"2010": 100.0}]}, {"Country Name": "St. Vincent and the Grenadines", "Country Code": "VCT", "years": [{"2010": 94.57567982}]}, {"Country Name": "Sub-Saharan Africa", "Country Code": "SSF", "years": [{"2010": 54.5669212978996}]}, {"Country Name": "Sub-Saharan Africa (IDA & IBRD countries)", "Country Code": "TSS", "years": [{"2010": 54.5669212978996}]}, {"Country Name": "Sub-Saharan Africa (excluding high income)", "Country Code": "SSA", "years": [{"2010": 54.5626815298601}]}, {"Country Name": "Sudan", "Country Code": "SDN", "years": [{"2010": 51.86921343}]}, {"Country Name": "Suriname", "Country Code": "SUR", "years": [{"2010": 93.53616993}]}, {"Country Name": "Sweden", "Country Code": "SWE", "years": [{"2010": 99.66207078}]}, {"Country Name": "Switzerland", "Country Code": "CHE", "years": [{"2010": 100.0}]}, {"Country Name": "Syrian Arab Republic", "Country Code": "SYR", "years": [{"2010": 93.02932562}]}, {"Country Name": "Tajikistan", "Country Code": "TJK", "years": [{"2010": 69.47196929}]}, {"Country Name": "Tanzania", "Country Code": "TZA", "years": [{"2010": 43.92815599}]}, {"Country Name": "Thailand", "Country Code": "THA", "years": [{"2010": 97.7144676}]}, {"Country Name": "Timor-Leste", "Country Code": "TLS", "years": [{"2010": 64.22163578}]}, {"Country Name": "Togo", "Country Code": "TGO", "years": [{"2010": 57.61240183}]}, {"Country Name": "Tonga", "Country Code": "TON", "years": [{"2010": 98.36656242}]}, {"Country Name": "Trinidad and Tobago", "Country Code": "TTO", "years": [{"2010": 95.77916246}]}, {"Country Name": "Tunisia", "Country Code": "TUN", "years": [{"2010": 92.22490194}]}, {"Country Name": "Turkiye", "Country Code": "TUR", "years": [{"2010": 95.41132275}]}, {"Country Name": "Turkmenistan", "Country Code": "TKM", "years": [{"2010": 94.14426188}]}, {"Country Name": "Turks and Caicos Islands", "Country Code": "TCA", "years": [{"2010": 92.08181818}]}, {"Country Name": "Tuvalu", "Country Code": "TUV", "years": [{"2010": 99.22682919}]}, {"Country Name": "Uganda", "Country Code": "UGA", "years": [{"2010": 40.2051887}]}, {"Country Name": "Ukraine", "Country Code": "UKR", "years": [{"2010": 95.07439751}]}, {"Country Name": "United Arab Emirates", "Country Code": "ARE", "years": [{"2010": 99.97133657}]}, {"Country Name": "United Kingdom", "Country Code": "GBR", "years": [{"2010": 99.99999846}]}, {"Country Name": "United States", "Country Code": "USA", "years": [{"2010": 98.97895208}]}, {"Country Name": "Upper middle income", "Country Code": "UMC", "years": [{"2010": 91.2568967967091}]}, {"Country Name": "Uruguay", "Country Code": "URY", "years": [{"2010": 98.3929266}]}, {"Country Name": "Uzbekistan", "Country Code": "UZB", "years": [{"2010": 96.12821048}]}, {"Country Name": "Vanuatu", "Country Code": "VUT", "years": [{"2010": 86.48624583}]}, {"Country Name": "Venezuela, RB", "Country Code": "VEN", "years": [{"2010": 95.45674931}]}, {"Country Name": "Vietnam", "Country Code": "VNM", "years": [{"2010": 88.86375815}]}, {"Country Name": "Virgin Islands (U.S.)", "Country Code": "VIR", "years": [{"2010": 98.7183}]}, {"Country Name": "West Bank and Gaza", "Country Code": "PSE", "years": [{"2010": 94.64840521}]}, {"Country Name": "World", "Country Code": "WLD", "years": [{"2010": 86.1470987940597}]}, {"Country Name": "Yemen, Rep.", "Country Code": "YEM", "years": [{"2010": 50.5280088}]}, {"Country Name": "Zambia", "Country Code": "ZMB", "years": [{"2010": 57.10021491}]}, {"Country Name": "Zimbabwe", "Country Code": "ZWE", "years": [{"2010": 67.54071095}]}]